yawp/__init__.py
yawp/__main__.py
yawp/docs/YAWP 2.2.0 User Manual.txt.pdf
yawp-2.2.0.dist-info/entry_points.txt
yawp-2.2.0.dist-info/licenses/LICENSE
yawp-2.2.0.dist-info/WHEEL
yawp-2.2.0.dist-info/METADATA
yawp-2.2.0.dist-info/RECORD
