Metadata-Version: 2.4
Name: yawp
Version: 2.2.0
Summary: Yet Another Word Processor, a Windows/Linux word processor for plain text files, with PDF export
Author-email: Carlo Alessandro Verre <carlo.alessandro.verre@gmail.com>
Requires-Python: >=3.6
Classifier: Programming Language :: Python :: 3
Classifier: Programming Language :: Python :: 3.6
Classifier: Development Status :: 5 - Production/Stable
Classifier: Environment :: Console
Classifier: Intended Audience :: Developers
Classifier: Intended Audience :: End Users/Desktop
Classifier: License :: OSI Approved :: GNU General Public License v3 or later (GPLv3+)
Classifier: Operating System :: POSIX :: Linux
License-File: LICENSE
Requires-Dist: FreeSimpleGUI==5.2.0.post1
Requires-Dist: pdfrw==0.4.0
Project-URL: Home, https://pypi.org/project/yawp
